LICENSE
README.md
setup.cfg
setup.py
mongoclass/__init__.py
mongoclass/cache.py
mongoclass/client.py
mongoclass/cursor.py
mongoclass.egg-info/PKG-INFO
mongoclass.egg-info/SOURCES.txt
mongoclass.egg-info/dependency_links.txt
mongoclass.egg-info/requires.txt
mongoclass.egg-info/top_level.txt