Metadata-Version: 2.1
Name: mongoclass
Version: 1.3
Summary: A basic ORM like interface for mongodb in python that uses dataclasses.
Home-page: https://github.com/bossauh/mongoclass
Download-URL: https://github.com/bossauh/mongoclass/archive/refs/tags/v_13.tar.gz
Author: Philippe Mathew
Author-email: philmattdev@gmail.com
License: MIT
Keywords: pymongo,orm
License-File: LICENSE
